j2escape/__init__.py
j2escape/j2escape.py
j2escape-1.0.2.dist-info/LICENSE
j2escape-1.0.2.dist-info/METADATA
j2escape-1.0.2.dist-info/WHEEL
j2escape-1.0.2.dist-info/entry_points.txt
j2escape-1.0.2.dist-info/RECORD
