Metadata-Version: 2.1
Name: j2escape
Version: 1.0.2
Summary: Jinja2 Template Escaper
Home-page: https://github.com/jifox/j2escape.git
License: Apache-2.0
Keywords: Cookiecutter,Cruft,Jinja2,Utility
Author: jifox
Author-email: josef.fuchs@j-fuchs.at
Requires-Python: >=3.7
Classifier: Development Status :: 5 - Production/Stable
Classifier: Intended Audience :: Developers
Classifier: License :: OSI Approved :: Apache Software License
Classifier: Operating System :: OS Independent
Classifier: Programming Language :: Python :: 3
Classifier: Programming Language :: Python :: 3.7
Classifier: Programming Language :: Python :: 3.8
Classifier: Programming Language :: Python :: 3.9
Classifier: Programming Language :: Python :: 3.10
Classifier: Programming Language :: Python :: 3.11
Classifier: Topic :: Software Development :: Libraries :: Python Modules
Classifier: Topic :: Utilities
Requires-Dist: jinja2 (>=3.1.2,<4.0.0)
Project-URL: Repository, https://github.com/jifox/j2escape.git
